maat/__init__.py
maat/exceptions.py
maat/extras.py
maat/maat.py
maat/transformations.py
maat/validations.py
maat/version.py
Maat-3.0.8.dist-info/LICENSE
Maat-3.0.8.dist-info/METADATA
Maat-3.0.8.dist-info/WHEEL
Maat-3.0.8.dist-info/top_level.txt
Maat-3.0.8.dist-info/RECORD
